{"is_source_file": false, "format": "", "description": "", "external_files": [], "external_methods": [], "published": [], "classes": [], "methods": [], "calls": [], "search-terms": [], "state": 2, "file_id": 11, "knowledge_revision": 66, "git_revision": "d4e1e7fb9a5df825677d51c90b31c7c75330fd4d", "hash": "815eb35ce890d591c20243648f562128", "format-version": 4, "code-base-name": "react_frontend", "filename": "react_frontend/eslint.config.mjs", "revision_history": [{"66": "d4e1e7fb9a5df825677d51c90b31c7c75330fd4d"}]}